kl.py
kl-4.0.2.dist-info/top_level.txt
kl-4.0.2.dist-info/DESCRIPTION.rst
kl-4.0.2.dist-info/RECORD
kl-4.0.2.dist-info/METADATA
kl-4.0.2.dist-info/WHEEL
kl-4.0.2.dist-info/metadata.json
