Metadata-Version: 2.0
Name: kl
Version: 4.0.2
Summary: Simple keylogger for Linux + X11
Home-page: https://github.com/surrealists/kl
Author: Cristian Cabrera
Author-email: surrealcristian@gmail.com
License: MIT
Keywords: keylogger linux x11
Platform: UNKNOWN
Classifier: Development Status :: 4 - Beta
Classifier: Environment :: Console
Classifier: Environment :: X11 Applications
Classifier: Intended Audience :: Developers
Classifier: Intended Audience :: End Users/Desktop
Classifier: License :: OSI Approved :: MIT License
Classifier: Natural Language :: English
Classifier: Operating System :: POSIX
Classifier: Programming Language :: Python
Classifier: Topic :: Software Development :: Libraries
Classifier: Topic :: System :: Monitoring
Classifier: Topic :: Utilities
